ncbulk/__init__.py
ncbulk/csv_io.py
ncbulk/main.py
ncbulk/nc_api.py
ncbulk/script.py
ncbulk-0.1.6.dist-info/licenses/LICENSE
ncbulk-0.1.6.dist-info/METADATA
ncbulk-0.1.6.dist-info/WHEEL
ncbulk-0.1.6.dist-info/entry_points.txt
ncbulk-0.1.6.dist-info/top_level.txt
ncbulk-0.1.6.dist-info/RECORD
