Metadata-Version: 2.4
Name: ncbulk
Version: 0.1.6
Summary: Nextcloud bulk user creation and update tool with CLI/TUI
Author: Jaguar Kovalev
License-Expression: Apache-2.0
Project-URL: Homepage, https://github.com/JaguarKovalev/nextcloud-bulk-users
Project-URL: Issues, https://github.com/JaguarKovalev/nextcloud-bulk-users/issues
Keywords: nextcloud,provisioning,ocs,csv,users,cli
Classifier: Programming Language :: Python :: 3
Classifier: Programming Language :: Python :: 3 :: Only
Classifier: Programming Language :: Python :: 3.12
Classifier: Environment :: Console
Classifier: Intended Audience :: System Administrators
Classifier: Topic :: System :: Systems Administration
Classifier: Topic :: Utilities
Requires-Python: >=3.12
License-File: LICENSE
Requires-Dist: requests>=2.31.0
Requires-Dist: python-dotenv>=1.0.1
Dynamic: license-file
